NuMeTriS/Graph_Class.py
NuMeTriS/Sparse_Graph_Class.py
NuMeTriS/Utility_Functions.py
NuMeTriS/Utility_Functions_sparse.py
NuMeTriS/__init__.py
NuMeTriS-0.1.1.dist-info/LICENSE
NuMeTriS-0.1.1.dist-info/METADATA
NuMeTriS-0.1.1.dist-info/WHEEL
NuMeTriS-0.1.1.dist-info/top_level.txt
NuMeTriS-0.1.1.dist-info/RECORD
