Metadata-Version: 2.1
Name: NuMeTriS
Version: 0.1.1
Summary: NuMeTris is a package for Maximum-Entropy models for triadic pattern detection. It contains known models such as DBCM and RBCM for binary motif analysis, and contain mixture models such as DBCM+CReMa and RBCM+CRWCM for weighted triadic motif analysis. The models are solved and routine are present for numeric ensemble generation and the computation of the triadic z-scores for triadic sub-graph occurrence, average flux and intensity.
Author-email: Marzio Di Vece <marzio.divece@imtlucca.it>
Project-URL: Homepage, https://github.com/MarsMDK/NuMeTriS
Keywords: maximum entropy methods,network motifs,pattern detection,graph,network,entropy
Classifier: License :: OSI Approved :: GNU General Public License v3 (GPLv3)
Classifier: Programming Language :: Python :: 3.9
Classifier: Programming Language :: Python :: 3.10
Requires-Python: >=3.9
License-File: LICENSE
Requires-Dist: numpy>=1.21.5
Requires-Dist: numba>=0.56.4
Requires-Dist: matplotlib>=3.6.1
Requires-Dist: tomli; python_version >= "3.9"
Provides-Extra: dev
Requires-Dist: pytest; extra == "dev"
